inventory_management/__init__.py
inventory_management/__meta__.py
inventory_management/py.typed
inventory_management/models/__init__.py
inventory_management/models/order_up_to.py
inventory_management-0.0.1.dist-info/LICENSE
inventory_management-0.0.1.dist-info/METADATA
inventory_management-0.0.1.dist-info/WHEEL
inventory_management-0.0.1.dist-info/top_level.txt
inventory_management-0.0.1.dist-info/RECORD
