Metadata-Version: 2.1
Name: inventory-management
Version: 0.0.1
Summary: UNKNOWN
Home-page: UNKNOWN
Author: Ian Eaves
Author-email: ian.k.eaves@gmail.com
License: MIT
Platform: UNKNOWN
Requires-Python: >=3.8
Requires-Dist: numpy
Provides-Extra: dev
Requires-Dist: twine ; extra == 'dev'
Requires-Dist: wheel (>=0.34.2) ; extra == 'dev'
Provides-Extra: test
Requires-Dist: pytest ; extra == 'test'
Requires-Dist: check-manifest (>=0.41) ; extra == 'test'
Requires-Dist: mypy ; extra == 'test'
Requires-Dist: black ; extra == 'test'
